laakhay/ta/__init__.py
laakhay/ta/exceptions.py
laakhay/ta/api/__init__.py
laakhay/ta/api/handle.py
laakhay/ta/api/namespace.py
laakhay/ta/catalog/__init__.py
laakhay/ta/catalog/catalog.py
laakhay/ta/catalog/params.py
laakhay/ta/catalog/serializer.py
laakhay/ta/catalog/type_parser.py
laakhay/ta/catalog/utils.py
laakhay/ta/core/__init__.py
laakhay/ta/core/bar.py
laakhay/ta/core/coercers.py
laakhay/ta/core/context.py
laakhay/ta/core/dataset.py
laakhay/ta/core/ohlcv.py
laakhay/ta/core/series.py
laakhay/ta/core/timestamps.py
laakhay/ta/core/types.py
laakhay/ta/data/__init__.py
laakhay/ta/data/csv.py
laakhay/ta/data/dataset.py
laakhay/ta/expr/__init__.py
laakhay/ta/expr/algebra/__init__.py
laakhay/ta/expr/algebra/alignment.py
laakhay/ta/expr/algebra/models.py
laakhay/ta/expr/algebra/operators.py
laakhay/ta/expr/dsl/__init__.py
laakhay/ta/expr/dsl/analyzer.py
laakhay/ta/expr/dsl/compiler.py
laakhay/ta/expr/dsl/nodes.py
laakhay/ta/expr/dsl/parser.py
laakhay/ta/expr/planner/__init__.py
laakhay/ta/expr/planner/builder.py
laakhay/ta/expr/planner/evaluator.py
laakhay/ta/expr/planner/manifest.py
laakhay/ta/expr/planner/planner.py
laakhay/ta/expr/planner/types.py
laakhay/ta/expr/runtime/__init__.py
laakhay/ta/expr/runtime/analyze.py
laakhay/ta/expr/runtime/capability_validator.py
laakhay/ta/expr/runtime/engine.py
laakhay/ta/expr/runtime/evaluator.py
laakhay/ta/expr/runtime/preview.py
laakhay/ta/expr/runtime/stream.py
laakhay/ta/expr/runtime/validate.py
laakhay/ta/indicators/__init__.py
laakhay/ta/indicators/events/__init__.py
laakhay/ta/indicators/events/channel.py
laakhay/ta/indicators/events/crossing.py
laakhay/ta/indicators/events/trend.py
laakhay/ta/indicators/momentum/__init__.py
laakhay/ta/indicators/momentum/rsi.py
laakhay/ta/indicators/momentum/stochastic.py
laakhay/ta/indicators/pattern/__init__.py
laakhay/ta/indicators/pattern/fib.py
laakhay/ta/indicators/pattern/swing.py
laakhay/ta/indicators/trend/__init__.py
laakhay/ta/indicators/trend/bbands.py
laakhay_ta-0.2.1.dist-info/METADATA
laakhay_ta-0.2.1.dist-info/WHEEL
laakhay_ta-0.2.1.dist-info/licenses/LICENSE
laakhay_ta-0.2.1.dist-info/RECORD
