Metadata-Version: 2.4
Name: laakhay-ta
Version: 0.2.1
Summary: Stateless Technical Analysis Library built with ♥︎ by Laakhay
Project-URL: Homepage, https://laakhay.com
Project-URL: Repository, https://github.com/laakhay/ta
Project-URL: Issues, https://github.com/laakhay/ta/issues
Author-email: Laakhay Corporation <laakhay.corp@gmail.com>
License: MIT
License-File: LICENSE
Requires-Python: >=3.12
Provides-Extra: dev
Requires-Dist: build>=1.0.0; extra == 'dev'
Requires-Dist: pyright>=1.1.406; extra == 'dev'
Requires-Dist: pytest-asyncio>=0.21.0; extra == 'dev'
Requires-Dist: pytest-cov>=7.0.0; extra == 'dev'
Requires-Dist: pytest>=8.0; extra == 'dev'
Requires-Dist: ruff>=0.1.0; extra == 'dev'
Requires-Dist: twine>=5.0.0; extra == 'dev'
